optus/__init__.py
optus/optus.py
optus-0.0.1.data/scripts/demo.py
optus-0.0.1.dist-info/LICENSE.md
optus-0.0.1.dist-info/METADATA
optus-0.0.1.dist-info/WHEEL
optus-0.0.1.dist-info/top_level.txt
optus-0.0.1.dist-info/RECORD
