Metadata-Version: 2.1
Name: optus
Version: 0.0.1
Summary: Python wrapper for the optus mobile API
Home-page: https://github.com/itchannel/optus-api
Author: itchannel
Author-email: steve@itchannel.me
License: MIT
Platform: UNKNOWN
Classifier: Programming Language :: Python :: 3.9
Classifier: Programming Language :: Python :: 3.8
Classifier: Programming Language :: Python :: 3.7
Classifier: Programming Language :: Python :: 3
Classifier: License :: OSI Approved :: MIT License
Classifier: Operating System :: OS Independent
Requires-Dist: requests
